sciplotlib/__init__.py
sciplotlib/__main__.py
sciplotlib/misc.py
sciplotlib/polish.py
sciplotlib/style.py
sciplotlib/text.py
sciplotlib/util.py
sciplotlib/main/myclass.py
sciplotlib/main/parser.py
sciplotlib/stylesheets/default.mplstyle
sciplotlib/stylesheets/economist.mplstyle
sciplotlib/stylesheets/nature-reviews-latex.mplstyle
sciplotlib/stylesheets/nature-reviews.mplstyle
sciplotlib/stylesheets/nature.mplstyle
sciplotlib-0.0.7.dist-info/METADATA
sciplotlib-0.0.7.dist-info/WHEEL
sciplotlib-0.0.7.dist-info/top_level.txt
sciplotlib-0.0.7.dist-info/RECORD
