Metadata-Version: 2.1
Name: sciplotlib
Version: 0.0.7
Summary: Custom functions to improve the look of matplotlib plots for scientific visualisation.
Home-page: https://github.com/Timothysit/sciplotlib
Author: Timothy Sit
Author-email: sitpakhang@gmail.com
Classifier: Operating System :: POSIX :: Linux
Classifier: License :: OSI Approved :: MIT License
Classifier: Programming Language :: Python :: 3.5
Classifier: Programming Language :: Python :: 3.6
Classifier: Programming Language :: Python :: 3.7
Requires-Dist: matplotlib
Requires-Dist: numpy
